Metadata-Version: 2.1
Name: pp-multifunctional
Version: 0.0.1
Summary: calc palindrome number, obtain PM2.5
Home-page: UNKNOWN
Author: 王熙元
Author-email: pipi@ydchp.com
License: MIT
Platform: UNKNOWN
Classifier: License :: OSI Approved :: MIT License
Classifier: Programming Language :: Python
Classifier: Programming Language :: Python :: 3
Classifier: Programming Language :: Python :: 3.6
Classifier: Programming Language :: Python :: Implementation :: CPython
Classifier: Programming Language :: Python :: Implementation :: PyPy
Requires-Python: >=3.6.0
